colocationpy/__init__.py
colocationpy/_version.py
colocationpy/metrics.py
colocationpy/transformations.py
colocationpy/utils.py
colocationpy-0.1.8.dist-info/licenses/LICENSE
colocationpy-0.1.8.dist-info/METADATA
colocationpy-0.1.8.dist-info/WHEEL
colocationpy-0.1.8.dist-info/top_level.txt
colocationpy-0.1.8.dist-info/RECORD
