Metadata-Version: 2.4
Name: colocationpy
Version: 0.1.8
Summary: Tools for co-location analysis: metrics, transforms, and utilities.
Author: Keiran Suchak
License: BSD 3-Clause License
Project-URL: Homepage, https://github.com/ksuchak1990/colocationpy/
Project-URL: Issues, https://github.com/ksuchak1990/colocationpy/issues
Keywords: co-location,spatial,mobility
Classifier: Programming Language :: Python :: 3
Classifier: Programming Language :: Python :: 3 :: Only
Classifier: Programming Language :: Python :: 3.10
Classifier: Programming Language :: Python :: 3.11
Classifier: Programming Language :: Python :: 3.12
Classifier: License :: OSI Approved :: BSD License
Classifier: Operating System :: OS Independent
Classifier: Typing :: Typed
Requires-Python: >=3.10
License-File: LICENSE
Requires-Dist: numpy<3.0,>=2.1
Requires-Dist: pandas<3.0,>=2.2.3
Requires-Dist: scipy<2.0,>=1.14.1
Requires-Dist: networkx<4.0,>=3.4
Requires-Dist: shapely<3.0,>=2.0.6
Requires-Dist: pandera<0.27,>=0.26.0
Provides-Extra: dev
Requires-Dist: pytest>=8.0; extra == "dev"
Requires-Dist: pytest-cov>=5.0; extra == "dev"
Requires-Dist: ruff>=0.5.0; extra == "dev"
Dynamic: license-file
